agentic_environments/__init__.py
agentic_environments/agentic_system.py
agentic_environments/environment.py
agentic_environments/model_output.py
agentic_environments/py.typed
agentic_environments/state.py
agentic_environments/tool_call_parsers/function_calling_models.py
agentic_environments/tool_call_parsers/tool_call_parser.py
agentic_environments/tool_call_parsers/xml_tags_with_yaml_content.py
agentic_environments-0.1.1.dist-info/METADATA
agentic_environments-0.1.1.dist-info/WHEEL
agentic_environments-0.1.1.dist-info/licenses/LICENSE
agentic_environments-0.1.1.dist-info/RECORD
