Metadata-Version: 2.4
Name: agentic-environments
Version: 0.1.1
Summary: Framework for building agentic environments with tool integration
Author-email: Daniel Austin <dan@aituning.ai>
License:     📄 MIT License - Non-Commercial Version  
License-File: LICENSE
Classifier: License :: Other/Proprietary License
Classifier: Operating System :: OS Independent
Classifier: Programming Language :: Python :: 3
Requires-Python: >=3.12
Requires-Dist: pyyaml>=6.0.2
